{"credit":"Made by ManningDesign","texture_size":[64,64],"textures":{"0":"furniturepack:furniture/summeressentials/bs_surf_board_orange_texture","particle":"furniturepack:furniture/summeressentials/bs_surf_board_orange_texture"},"elements":[{"from":[2,-0.83524,8.69906],"to":[14,31.16476,9.69906],"rotation":{"angle":22.5,"axis":"x","origin":[6,15.16476,9.69906]},"faces":{"north":{"uv":[0,0,3,8],"texture":"#0"},"east":{"uv":[3.25,8,3.5,16],"texture":"#0"},"south":{"uv":[3,0,0,8],"texture":"#0"},"west":{"uv":[3.5,8,3.75,16],"texture":"#0"},"up":{"uv":[8,8.5,5,8.25],"texture":"#0"},"down":{"uv":[11,8.25,8,8.5],"texture":"#0"}}},{"from":[1.7,-1.13524,8.39906],"to":[14.3,31.46476,9.99906],"rotation":{"angle":22.5,"axis":"x","origin":[6,15.16476,9.69906]},"faces":{"north":{"uv":[6,0,9,8],"texture":"#0"},"east":{"uv":[4.25,8,4.5,16],"texture":"#0"},"south":{"uv":[9,0,6,8],"texture":"#0"},"west":{"uv":[4.75,8,5,16],"texture":"#0"},"up":{"uv":[8,9,5,8.75],"texture":"#0"},"down":{"uv":[11,8.75,8,9],"texture":"#0"}}},{"from":[7,8.33438,5.57693],"to":[9,9.33438,8.57693],"rotation":{"angle":-45,"axis":"x","origin":[8,8.83438,5.57693]},"faces":{"north":{"uv":[6,9,6.5,9.25],"texture":"#0"},"east":{"uv":[9,5.5,9.75,5.75],"texture":"#0"},"south":{"uv":[9,6,9.5,6.25],"texture":"#0"},"west":{"uv":[9,5.75,9.75,6],"texture":"#0"},"up":{"uv":[9.5,4.75,9,4],"texture":"#0"},"down":{"uv":[9.5,4.75,9,5.5],"texture":"#0"}}},{"from":[7,6.33438,0.57693],"to":[9,9.33438,5.57693],"rotation":{"angle":-45,"axis":"x","origin":[8,8.83438,5.57693]},"faces":{"north":{"uv":[5,9,5.5,9.75],"texture":"#0"},"east":{"uv":[9,0,10.25,0.75],"texture":"#0"},"south":{"uv":[5.5,9,6,9.75],"texture":"#0"},"west":{"uv":[9,0.75,10.25,1.5],"texture":"#0"},"up":{"uv":[9.5,2.75,9,1.5],"texture":"#0"},"down":{"uv":[9.5,2.75,9,4],"texture":"#0"}}}],"display":{"thirdperson_righthand":{"rotation":[83,115,-90],"translation":[0.5,-10.75,3.5]},"thirdperson_lefthand":{"rotation":[83,115,-90],"translation":[0.5,-10.75,3.5]},"firstperson_righthand":{"rotation":[0,110,0],"translation":[0.5,2,0],"scale":[0.37,0.37,0.37]},"firstperson_lefthand":{"rotation":[0,110,0],"translation":[0.5,2,0],"scale":[0.37,0.37,0.37]},"gui":{"rotation":[1,138,0],"translation":[-0.5,-3.5,0],"scale":[0.44,0.44,0.44]},"head":{"rotation":[-112,0,0],"translation":[0,9,10.25],"scale":[1.41,1.41,1.41]},"fixed":{"rotation":[-90,0,0],"translation":[0,0,-16],"scale":[2.01,2.01,2.01]}}}